[
  {
    "header": {
      "userId": "1d62ced10737cebe0b1723eddd3bb5c9",
      "scriptVersion": 1.8
    },
    "data": [
      {
        "timestamp": 1390003622000,
        "lon": 2.94920013,
        "accuracy": 119,
        "speed": 0,
        "lat": 50.59609544
      },
      {
        "timestamp": 1390003856000,
        "lon": 2.94936274,
        "accuracy": 166,
        "speed": 0,
        "lat": 50.59671888
      },
      {
        "timestamp": 1390004052000,
        "lon": 2.94916971,
        "accuracy": 63,
        "speed": 0,
        "lat": 50.59609109
      },
      {
        "timestamp": 1390004112000,
        "lon": 2.94905106,
        "accuracy": 63,
        "speed": 0,
        "lat": 50.59551427
      },
      {
        "timestamp": 1390004169000,
        "lon": 2.94906477,
        "accuracy": 89,
        "speed": 0,
        "lat": 50.59635711
      },
      {
        "timestamp": 1390005951927,
        "lon": 2.95004948,
        "accuracy": 88,
        "speed": 0.5,
        "lat": 50.59598772
      },
      {
        "timestamp": 1390006158000,
        "lon": 2.94929937,
        "accuracy": 141,
        "speed": 0,
        "lat": 50.59650899
      },
      {
        "timestamp": 1390016632959,
        "lon": 2.94971895,
        "accuracy": 101,
        "speed": 1.25,
        "lat": 50.5970622
      },
      {
        "timestamp": 1390016707000,
        "lon": 2.94947038,
        "accuracy": 88,
        "speed": 0,
        "lat": 50.59585315
      },
      {
        "timestamp": 1390016782039,
        "lon": 2.95019192,
        "accuracy": 112,
        "speed": 0.75,
        "lat": 50.5960848
      },
      {
        "timestamp": 1390016811958,
        "lon": 2.94950154,
        "accuracy": 46,
        "speed": 1,
        "lat": 50.59634208
      },
      {
        "timestamp": 1390017233010,
        "lon": 2.94978884,
        "accuracy": 103,
        "speed": 1.25,
        "lat": 50.59681665
      },
      {
        "timestamp": 1390017329000,
        "lon": 2.95025438,
        "accuracy": 59,
        "speed": 0,
        "lat": 50.59810134
      },
      {
        "timestamp": 1390017359000,
        "lon": 2.94983047,
        "accuracy": 60,
        "speed": 0,
        "lat": 50.5970521
      },
      {
        "timestamp": 1390017413000,
        "lon": 2.94904065,
        "accuracy": 59,
        "speed": 0,
        "lat": 50.59636456
      },
      {
        "timestamp": 1390017474000,
        "lon": 2.94936501,
        "accuracy": 113,
        "speed": 0,
        "lat": 50.5968819
      },
      {
        "timestamp": 1390017707995,
        "lon": 2.9492807,
        "accuracy": 44,
        "speed": 0.5,
        "lat": 50.59634342
      },
      {
        "timestamp": 1390018073000,
        "lon": 2.94932958,
        "accuracy": 16,
        "speed": 0,
        "lat": 50.5970407
      },
      {
        "timestamp": 1390018133000,
        "lon": 2.94872728,
        "accuracy": 36,
        "speed": 0,
        "lat": 50.59611227
      },
      {
        "timestamp": 1390018195002,
        "lon": 2.94931902,
        "accuracy": 116,
        "speed": 0,
        "lat": 50.59655594
      },
      {
        "timestamp": 1390018373000,
        "lon": 2.94916163,
        "accuracy": 55,
        "speed": 0,
        "lat": 50.59608747
      },
      {
        "timestamp": 1390018607970,
        "lon": 2.94948914,
        "accuracy": 44,
        "speed": 0.25,
        "lat": 50.59656338
      },
      {
        "timestamp": 1390018737978,
        "lon": 2.94890034,
        "accuracy": 55,
        "speed": 2.25,
        "lat": 50.59601678
      },
      {
        "timestamp": 1390018977008,
        "lon": 2.94937736,
        "accuracy": 142,
        "speed": 1.5,
        "lat": 50.59659686
      },
      {
        "timestamp": 1390019651000,
        "lon": 2.94978135,
        "accuracy": 33,
        "speed": 0,
        "lat": 50.59738963
      },
      {
        "timestamp": 1390019770982,
        "lon": 2.94901971,
        "accuracy": 66,
        "speed": 1.25,
        "lat": 50.59620296
      },
      {
        "timestamp": 1390019828033,
        "lon": 2.94988106,
        "accuracy": 40,
        "speed": 0.25,
        "lat": 50.59684673
      },
      {
        "timestamp": 1390019889990,
        "lon": 2.94930367,
        "accuracy": 15,
        "speed": 0.5,
        "lat": 50.59626335
      },
      {
        "timestamp": 1390020489997,
        "lon": 2.94944721,
        "accuracy": 28,
        "speed": 0,
        "lat": 50.59673998
      },
      {
        "timestamp": 1390020548983,
        "lon": 2.94909899,
        "accuracy": 70,
        "speed": 0,
        "lat": 50.59627187
      },
      {
        "timestamp": 1390020770000,
        "lon": 2.94941102,
        "accuracy": 149,
        "speed": 0,
        "lat": 50.59689379
      },
      {
        "timestamp": 1390020798000,
        "lon": 2.94917663,
        "accuracy": 75,
        "speed": 0,
        "lat": 50.59646532
      },
      {
        "timestamp": 1390021090002,
        "lon": 2.94956411,
        "accuracy": 61,
        "speed": 0.25,
        "lat": 50.59706426
      },
      {
        "timestamp": 1390021210005,
        "lon": 2.94920315,
        "accuracy": 8,
        "speed": 0.5,
        "lat": 50.59648583
      },
      {
        "timestamp": 1390021510008,
        "lon": 2.94936752,
        "accuracy": 32,
        "speed": 0,
        "lat": 50.59692669
      },
      {
        "timestamp": 1390021631989,
        "lon": 2.94913612,
        "accuracy": 31,
        "speed": 2.25,
        "lat": 50.59627155
      },
      {
        "timestamp": 1390021746095,
        "lon": 2.94964688,
        "accuracy": 49,
        "speed": 0.25,
        "lat": 50.59687135
      },
      {
        "timestamp": 1390021810010,
        "lon": 2.94940771,
        "accuracy": 13,
        "speed": 0,
        "lat": 50.59619864
      },
      {
        "timestamp": 1390022527048,
        "lon": 2.94943185,
        "accuracy": 34,
        "speed": 0.7071067690849304,
        "lat": 50.5969416
      },
      {
        "timestamp": 1390023844997,
        "lon": 2.94926149,
        "accuracy": 50,
        "speed": 2.25,
        "lat": 50.59644847
      },
      {
        "timestamp": 1390024204985,
        "lon": 2.94882189,
        "accuracy": 21,
        "speed": 0.5,
        "lat": 50.59699061
      },
      {
        "timestamp": 1390024269018,
        "lon": 2.94917367,
        "accuracy": 104,
        "speed": 0,
        "lat": 50.59631996
      },
      {
        "timestamp": 1390024327049,
        "lon": 2.949369,
        "accuracy": 31,
        "speed": 2.25,
        "lat": 50.59679862
      },
      {
        "timestamp": 1390024869089,
        "lon": 2.94964213,
        "accuracy": 25,
        "speed": 1.25,
        "lat": 50.59614059
      },
      {
        "timestamp": 1390025780064,
        "lon": 2.94946654,
        "accuracy": 56,
        "speed": 0.5,
        "lat": 50.5965925
      },
      {
        "timestamp": 1390026015120,
        "lon": 2.94891625,
        "accuracy": 90,
        "speed": 0.5,
        "lat": 50.59609068
      },
      {
        "timestamp": 1390026072988,
        "lon": 2.94938109,
        "accuracy": 60,
        "speed": 0.5,
        "lat": 50.59655753
      },
      {
        "timestamp": 1390026248930,
        "lon": 2.94912316,
        "accuracy": 26,
        "speed": 0.25,
        "lat": 50.59697867
      },
      {
        "timestamp": 1390026370059,
        "lon": 2.94937107,
        "accuracy": 28,
        "speed": 0,
        "lat": 50.59637112
      },
      {
        "timestamp": 1390027093119,
        "lon": 2.9496682,
        "accuracy": 67,
        "speed": 0.75,
        "lat": 50.59677922
      },
      {
        "timestamp": 1390027328025,
        "lon": 2.94870077,
        "accuracy": 62,
        "speed": 0,
        "lat": 50.59693382
      },
      {
        "timestamp": 1390027396070,
        "lon": 2.94963607,
        "accuracy": 53,
        "speed": 0.75,
        "lat": 50.59644457
      },
      {
        "timestamp": 1390027748145,
        "lon": 2.94956319,
        "accuracy": 37,
        "speed": 0.25,
        "lat": 50.59694954
      },
      {
        "timestamp": 1390028056077,
        "lon": 2.94890172,
        "accuracy": 71,
        "speed": 0.75,
        "lat": 50.59666124
      },
      {
        "timestamp": 1390028589230,
        "lon": 2.95095639,
        "accuracy": 99,
        "speed": 0.25,
        "lat": 50.59690912
      },
      {
        "timestamp": 1390028652000,
        "lon": 2.94942658,
        "accuracy": 65,
        "speed": 0,
        "lat": 50.59650779
      },
      {
        "timestamp": 1390028714156,
        "lon": 2.95006884,
        "accuracy": 84,
        "speed": 1.25,
        "lat": 50.59688354
      },
      {
        "timestamp": 1390028773000,
        "lon": 2.94923835,
        "accuracy": 67,
        "speed": 0,
        "lat": 50.59685237
      },
      {
        "timestamp": 1390028827119,
        "lon": 2.94986106,
        "accuracy": 38,
        "speed": 0.75,
        "lat": 50.59660232
      },
      {
        "timestamp": 1390028890085,
        "lon": 2.94915795,
        "accuracy": 25,
        "speed": 0.5,
        "lat": 50.59652284
      },
      {
        "timestamp": 1390031047976,
        "lon": 2.94830052,
        "accuracy": 71,
        "speed": 0.25,
        "lat": 50.59654708
      },
      {
        "timestamp": 1390031112109,
        "lon": 2.94940907,
        "accuracy": 15,
        "speed": 0.5,
        "lat": 50.59642919
      },
      {
        "timestamp": 1390031529041,
        "lon": 2.94850478,
        "accuracy": 19,
        "speed": 0.5,
        "lat": 50.59653163
      },
      {
        "timestamp": 1390031657000,
        "lon": 2.94926133,
        "accuracy": 20,
        "speed": 0,
        "lat": 50.59635948
      },
      {
        "timestamp": 1390032132000,
        "lon": 2.94928938,
        "accuracy": 72,
        "speed": 0,
        "lat": 50.59680964
      },
      {
        "timestamp": 1390032316123,
        "lon": 2.94926929,
        "accuracy": 5,
        "speed": 0.5,
        "lat": 50.596337
      },
      {
        "timestamp": 1390032560046,
        "lon": 2.9495202,
        "accuracy": 130,
        "speed": 1,
        "lat": 50.59714764
      },
      {
        "timestamp": 1390032589122,
        "lon": 2.94934846,
        "accuracy": 121,
        "speed": 0.75,
        "lat": 50.59664555
      },
      {
        "timestamp": 1390032633137,
        "lon": 2.95012961,
        "accuracy": 40,
        "speed": 0.75,
        "lat": 50.59649323
      },
      {
        "timestamp": 1390032700126,
        "lon": 2.94923692,
        "accuracy": 36,
        "speed": 0.5,
        "lat": 50.59677311
      },
      {
        "timestamp": 1390034803000,
        "lon": 2.94954272,
        "accuracy": 137,
        "speed": 0,
        "lat": 50.59631029
      },
      {
        "timestamp": 1390035801113,
        "lon": 2.94904094,
        "accuracy": 29,
        "speed": 0.5,
        "lat": 50.5968341
      },
      {
        "timestamp": 1390035863000,
        "lon": 2.94937346,
        "accuracy": 24,
        "speed": 0,
        "lat": 50.59632505
      },
      {
        "timestamp": 1390036222163,
        "lon": 2.9493085,
        "accuracy": 50,
        "speed": 0.5,
        "lat": 50.59690216
      },
      {
        "timestamp": 1390036951000,
        "lon": 2.94940671,
        "accuracy": 112,
        "speed": 0,
        "lat": 50.59643069
      },
      {
        "timestamp": 1390038996000,
        "lon": 2.94942147,
        "accuracy": 117,
        "speed": 0,
        "lat": 50.59690221
      },
      {
        "timestamp": 1390039231000,
        "lon": 2.94911559,
        "accuracy": 38,
        "speed": 0,
        "lat": 50.59648784
      },
      {
        "timestamp": 1390039292000,
        "lon": 2.94958673,
        "accuracy": 126,
        "speed": 0,
        "lat": 50.5969248
      },
      {
        "timestamp": 1390039729074,
        "lon": 2.94807475,
        "accuracy": 133,
        "speed": 0.25,
        "lat": 50.59675641
      },
      {
        "timestamp": 1390039785212,
        "lon": 2.94996404,
        "accuracy": 74,
        "speed": 1,
        "lat": 50.5965316
      },
      {
        "timestamp": 1390039834000,
        "lon": 2.94915265,
        "accuracy": 113,
        "speed": 0,
        "lat": 50.59649944
      },
      {
        "timestamp": 1390039903000,
        "lon": 2.949726,
        "accuracy": 122,
        "speed": 0,
        "lat": 50.59677597
      },
      {
        "timestamp": 1390040015000,
        "lon": 2.94930044,
        "accuracy": 52,
        "speed": 0,
        "lat": 50.5963075
      },
      {
        "timestamp": 1390040134206,
        "lon": 2.94955964,
        "accuracy": 28,
        "speed": 1.25,
        "lat": 50.59675511
      },
      {
        "timestamp": 1390040747000,
        "lon": 2.94899205,
        "accuracy": 34,
        "speed": 0,
        "lat": 50.59640022
      },
      {
        "timestamp": 1390040795000,
        "lon": 2.94948617,
        "accuracy": 17,
        "speed": 0,
        "lat": 50.59680702
      },
      {
        "timestamp": 1390042013000,
        "lon": 2.94917031,
        "accuracy": 17,
        "speed": 0,
        "lat": 50.59637339
      },
      {
        "timestamp": 1390042427193,
        "lon": 2.94897612,
        "accuracy": 24,
        "speed": 0,
        "lat": 50.59685524
      },
      {
        "timestamp": 1390043162000,
        "lon": 2.94954609,
        "accuracy": 108,
        "speed": 0,
        "lat": 50.59649585
      },
      {
        "timestamp": 1390044113000,
        "lon": 2.94933469,
        "accuracy": 22,
        "speed": 0,
        "lat": 50.59702683
      },
      {
        "timestamp": 1390044473000,
        "lon": 2.9490135,
        "accuracy": 21,
        "speed": 0,
        "lat": 50.59649471
      },
      {
        "timestamp": 1390044903291,
        "lon": 2.94954061,
        "accuracy": 137,
        "speed": 0.5,
        "lat": 50.59688309
      },
      {
        "timestamp": 1390045368195,
        "lon": 2.94872394,
        "accuracy": 52,
        "speed": 0.5,
        "lat": 50.5966236
      },
      {
        "timestamp": 1390045492263,
        "lon": 2.94942033,
        "accuracy": 23,
        "speed": 0.5,
        "lat": 50.59681426
      },
      {
        "timestamp": 1390045991326,
        "lon": 2.94966368,
        "accuracy": 98,
        "speed": 0.5,
        "lat": 50.59628597
      },
      {
        "timestamp": 1390046081262,
        "lon": 2.94933472,
        "accuracy": 58,
        "speed": 0.75,
        "lat": 50.59674402
      },
      {
        "timestamp": 1390048574000,
        "lon": 2.94953611,
        "accuracy": 149,
        "speed": 0,
        "lat": 50.5972277
      },
      {
        "timestamp": 1390048741000,
        "lon": 2.94939079,
        "accuracy": 55,
        "speed": 0,
        "lat": 50.59652432
      },
      {
        "timestamp": 1390049099000,
        "lon": 2.94935989,
        "accuracy": 13,
        "speed": 0,
        "lat": 50.59705266
      },
      {
        "timestamp": 1390049283000,
        "lon": 2.94930459,
        "accuracy": 126,
        "speed": 0,
        "lat": 50.59653239
      },
      {
        "timestamp": 1390050069000,
        "lon": 2.94968439,
        "accuracy": 149,
        "speed": 0,
        "lat": 50.59697557
      },
      {
        "timestamp": 1390051278000,
        "lon": 2.94932093,
        "accuracy": 141,
        "speed": 0,
        "lat": 50.59654287
      },
      {
        "timestamp": 1390051439000,
        "lon": 2.94965662,
        "accuracy": 145,
        "speed": 0,
        "lat": 50.59710686
      },
      {
        "timestamp": 1390051668000,
        "lon": 2.94924412,
        "accuracy": 79,
        "speed": 0,
        "lat": 50.5964264
      },
      {
        "timestamp": 1390051976000,
        "lon": 2.9493979,
        "accuracy": 138,
        "speed": 0,
        "lat": 50.59698143
      },
      {
        "timestamp": 1390052215384,
        "lon": 2.94964973,
        "accuracy": 101,
        "speed": 2.5,
        "lat": 50.59580766
      },
      {
        "timestamp": 1390052281000,
        "lon": 2.94961068,
        "accuracy": 106,
        "speed": 0,
        "lat": 50.5964336
      },
      {
        "timestamp": 1390053155345,
        "lon": 2.94919567,
        "accuracy": 23,
        "speed": 1.25,
        "lat": 50.59682904
      },
      {
        "timestamp": 1390053397000,
        "lon": 2.94940513,
        "accuracy": 20,
        "speed": 0,
        "lat": 50.59631816
      },
      {
        "timestamp": 1390053814352,
        "lon": 2.94934008,
        "accuracy": 20,
        "speed": 0.75,
        "lat": 50.59676616
      },
      {
        "timestamp": 1390055160000,
        "lon": 2.9491173,
        "accuracy": 133,
        "speed": 0,
        "lat": 50.597319
      },
      {
        "timestamp": 1390055195365,
        "lon": 2.94954729,
        "accuracy": 9,
        "speed": 0.5,
        "lat": 50.59654959
      },
      {
        "timestamp": 1390058863358,
        "lon": 2.94892753,
        "accuracy": 74,
        "speed": 0.5,
        "lat": 50.59678439
      },
      {
        "timestamp": 1390059113000,
        "lon": 2.94958454,
        "accuracy": 45,
        "speed": 0,
        "lat": 50.59633209
      },
      {
        "timestamp": 1390059349000,
        "lon": 2.94962777,
        "accuracy": 76,
        "speed": 0,
        "lat": 50.59691153
      },
      {
        "timestamp": 1390060510423,
        "lon": 2.94960618,
        "accuracy": 143,
        "speed": 1.25,
        "lat": 50.59637489
      },
      {
        "timestamp": 1390060899429,
        "lon": 2.94973278,
        "accuracy": 96,
        "speed": 1,
        "lat": 50.59694261
      },
      {
        "timestamp": 1390061552000,
        "lon": 2.94941615,
        "accuracy": 169,
        "speed": 0,
        "lat": 50.59650214
      },
      {
        "timestamp": 1390063922466,
        "lon": 2.94939321,
        "accuracy": 135,
        "speed": 1.5,
        "lat": 50.59718215
      },
      {
        "timestamp": 1390064032405,
        "lon": 2.94943053,
        "accuracy": 76,
        "speed": 0.25,
        "lat": 50.59633999
      },
      {
        "timestamp": 1390064625423,
        "lon": 2.94887539,
        "accuracy": 91,
        "speed": 0.5,
        "lat": 50.59593171
      },
      {
        "timestamp": 1390064688000,
        "lon": 2.9494378,
        "accuracy": 119,
        "speed": 0,
        "lat": 50.59636052
      },
      {
        "timestamp": 1390064930505,
        "lon": 2.94999924,
        "accuracy": 111,
        "speed": 1,
        "lat": 50.596681
      },
      {
        "timestamp": 1390065294000,
        "lon": 2.94914714,
        "accuracy": 143,
        "speed": 0,
        "lat": 50.59650695
      },
      {
        "timestamp": 1390066720489,
        "lon": 2.94930247,
        "accuracy": 29,
        "speed": 0.5,
        "lat": 50.59590751
      },
      {
        "timestamp": 1390066779527,
        "lon": 2.94947191,
        "accuracy": 24,
        "speed": 0.5,
        "lat": 50.59635541
      },
      {
        "timestamp": 1390068527000,
        "lon": 2.94939183,
        "accuracy": 59,
        "speed": 0,
        "lat": 50.59684125
      },
      {
        "timestamp": 1390068646510,
        "lon": 2.94944946,
        "accuracy": 46,
        "speed": 2,
        "lat": 50.59749546
      },
      {
        "timestamp": 1390068708000,
        "lon": 2.9491163,
        "accuracy": 114,
        "speed": 0.75,
        "lat": 50.59703535
      },
      {
        "timestamp": 1390069223000,
        "lon": 2.9491824,
        "accuracy": 103,
        "speed": 0,
        "lat": 50.59635935
      },
      {
        "timestamp": 1390069336517,
        "lon": 2.94953203,
        "accuracy": 55,
        "speed": 0.5,
        "lat": 50.59685542
      },
      {
        "timestamp": 1390070266526,
        "lon": 2.94930689,
        "accuracy": 54,
        "speed": 0.25,
        "lat": 50.59629574
      },
      {
        "timestamp": 1390070803000,
        "lon": 2.94942813,
        "accuracy": 88,
        "speed": 0,
        "lat": 50.59686577
      },
      {
        "timestamp": 1390071039428,
        "lon": 2.94853091,
        "accuracy": 109,
        "speed": 0.25,
        "lat": 50.59724209
      },
      {
        "timestamp": 1390071097528,
        "lon": 2.94930325,
        "accuracy": 88,
        "speed": 0.25,
        "lat": 50.59669685
      },
      {
        "timestamp": 1390071583000,
        "lon": 2.94955343,
        "accuracy": 80,
        "speed": 0,
        "lat": 50.59732148
      },
      {
        "timestamp": 1390071653000,
        "lon": 2.94935963,
        "accuracy": 115,
        "speed": 0,
        "lat": 50.59649551
      },
      {
        "timestamp": 1390071705000,
        "lon": 2.94923138,
        "accuracy": 147,
        "speed": 0,
        "lat": 50.59603538
      },
      {
        "timestamp": 1390071757529,
        "lon": 2.94926724,
        "accuracy": 72,
        "speed": 1,
        "lat": 50.59659221
      },
      {
        "timestamp": 1390071826000,
        "lon": 2.9492949,
        "accuracy": 135,
        "speed": 0,
        "lat": 50.59587106
      },
      {
        "timestamp": 1390071934000,
        "lon": 2.94933145,
        "accuracy": 177,
        "speed": 0,
        "lat": 50.59647029
      },
      {
        "timestamp": 1390072549000,
        "lon": 2.9496228,
        "accuracy": 90,
        "speed": 0,
        "lat": 50.59691976
      },
      {
        "timestamp": 1390072608000,
        "lon": 2.94950387,
        "accuracy": 69,
        "speed": 0,
        "lat": 50.59643551
      },
      {
        "timestamp": 1390080644000,
        "lon": 2.9493004,
        "accuracy": 140,
        "speed": 0,
        "lat": 50.59692263
      },
      {
        "timestamp": 1390080724639,
        "lon": 2.94930967,
        "accuracy": 28,
        "speed": 0.25,
        "lat": 50.59635033
      },
      {
        "timestamp": 1390081752000,
        "lon": 2.94926342,
        "accuracy": 142,
        "speed": 0,
        "lat": 50.59682875
      },
      {
        "timestamp": 1390083308664,
        "lon": 2.94968287,
        "accuracy": 59,
        "speed": 1.75,
        "lat": 50.59626753
      },
      {
        "timestamp": 1390083797684,
        "lon": 2.94951046,
        "accuracy": 94,
        "speed": 1,
        "lat": 50.59681619
      },
      {
        "timestamp": 1390083840000,
        "lon": 2.94919671,
        "accuracy": 26,
        "speed": 0,
        "lat": 50.59626949
      },
      {
        "timestamp": 1390084015705,
        "lon": 2.94974575,
        "accuracy": 45,
        "speed": 0,
        "lat": 50.59662411
      },
      {
        "timestamp": 1390084229000,
        "lon": 2.94938651,
        "accuracy": 129,
        "speed": 0,
        "lat": 50.59701763
      },
      {
        "timestamp": 1390084324678,
        "lon": 2.9496565,
        "accuracy": 46,
        "speed": 1,
        "lat": 50.59625113
      },
      {
        "timestamp": 1390084803000,
        "lon": 2.94964682,
        "accuracy": 126,
        "speed": 0,
        "lat": 50.59670339
      }
    ]
  }
]